Metadata-Version: 2.1
Name: gitdown
Version: 1.1.10
Summary: A tool to download sub-dirs from github.
Home-page: https://github.com/jmhIcoding/GitDown
Author: jiangminghao
Author-email: jiangminghao@iie.ac.cn
License: UNKNOWN
Platform: UNKNOWN
Classifier: Programming Language :: Python :: 3
